pandance/__init__.py
pandance/pandance.py
pandance-0.3.0.dist-info/LICENSE
pandance-0.3.0.dist-info/METADATA
pandance-0.3.0.dist-info/WHEEL
pandance-0.3.0.dist-info/top_level.txt
pandance-0.3.0.dist-info/RECORD
