Metadata-Version: 2.1
Name: pandance
Version: 0.3.0
Summary: Advanced relational operations for pandas DataFrames
Author: Filip Buric
Maintainer: Filip Buric
Project-URL: Homepage, https://pandance.readthedocs.io
Project-URL: Documentation, https://pandance.readthedocs.io
Project-URL: Source Code, https://github.com/fburic/pandance
Classifier: Intended Audience :: Developers
Classifier: Intended Audience :: Education
Classifier: Intended Audience :: Science/Research
Classifier: Programming Language :: Python :: 3
Classifier: Topic :: Database
Classifier: Topic :: Scientific/Engineering 
Classifier: License :: OSI Approved :: BSD License
Classifier: Operating System :: OS Independent
Requires-Python: >=3.8
License-File: LICENSE
Requires-Dist: setuptools (>=42)
Requires-Dist: pandas (>=1.2.0)
Requires-Dist: intervaltree (==3.1.0)
Requires-Dist: psutil (>=5.9.0)
